bh_deedoo/__main__.py
bh_deedoo/cmds/__hide/deedoo/__init__.py
bh_deedoo/cmds/__hide/deedoo/defaults.py
bh_deedoo/cmds/__hide/deedoo/server.py
bh_deedoo/cmds/__hide/deedoo/stoppers.py
bh_deedoo/cmds/__hide/deedoo/util.py
bh_deedoo/cmds/deedoo/__init__.py
bh_deedoo/cmds/deedoo/main.py
bh_deedoo/cmds/deedoo/test_deedoo.py
bh_deedoo/cmds/deedoo/lib/debug.py
bh_deedoo/cmds/deedoo/lib/kill.py
bh_deedoo/cmds/deedoo/lib/stop.py
bh_deedoo/cmds/deedoo/lib/util.py
bh_deedoo-0.0.4b0.dist-info/METADATA
bh_deedoo-0.0.4b0.dist-info/WHEEL
bh_deedoo-0.0.4b0.dist-info/entry_points.txt
bh_deedoo-0.0.4b0.dist-info/top_level.txt
bh_deedoo-0.0.4b0.dist-info/RECORD
